Workbook

Sheet Budget Calculator
A1: Rural Connectivity Budget Tool | J1: to put on https://bridgedesignv3.streamlit.app/Bridge_Price_Estimation
A2: This tool helps transport planners, financiers, and policymakers explore how a small share of a larger transport project budget (like a large corridor investment) could fund essential Rural Networked Transport Infrastructure (RNTI) — the trail bridges, footpaths, low-water crossings, ancillary safety, and active mobility components that connect rural communities to primary networks. RNTI is defined and detailed in Segerberg & Noriega (2026), Advancing Inclusive, Multimodal, Climate-Resilient Planning for Rural Networked Transport Infrastructure. The calculator is designed to raise awareness of how modest, evidence-based RNTI add-ons — typically 1% to 10% of a transport project budget — can meaningfully improve resilience, market access, and equity outcomes for the roughly 3 billion people living in rural/semi-rural areas worldwide. To use the tool, enter your total project budget, the percentage you want to allocate to RNTI, and an optional maintenance reserve. Then enter quantities next to any of the RNTI components you would like to fund. The calculator returns total estimated costs, a remaining budget, and a summary of your allocation. Unit cost ranges are approximations using blended averages from available, verifiable sources. This version is an illustrative, back-of-the-envelope tool using high-level cost estimates.
A4: This is an initial version of the Rural Connectivity Budget Tool. Estimated budgets are approximations based on blended averages of publicly available cost data and may not reflect local market conditions, terrain, labor rates, or design specifications in any specific country or project. Fika will integrate more nuanced cost approximations and social and climate impact information in future iterations of this tool. Suggestions, corrections, additional cost data, and inquiries are warmly welcomed — contact our research team here.
B7: SECTION 1: TRANSPORT PROJECT INPUTS
B8: [Info for Cameron/Youdahe Only -- the editable fields in the calculator tool should be the ones in yellow below]
B9: Project Name / Description
B10: Country / Region
B12: Total Transport Project Budget (USD) | C12: 0
B13: % Allocated to RNTI / Rural Access | C13: 0
B14: RNTI Budget Available | C14: =C12*C13 -> 0
B16: Maintenance Reserve (%) | C16: 0 | D16: Recommended: 5-15% of RNTI budget
B17: Maintenance Reserve Amount | C17: =C14*C16 -> 0
B18: Capital Budget for Infrastructure | C18: =C14-C17 -> 0
B21: SECTION 2: INFRASTRUCTURE MIX — Enter desired quantities in column G
B22: [Info for Cameron/Youdahe Only -- Unit costs link directly from the 'Source Data' sheet blended averages. Brooke and I are adjusting]
A23: # | B23: Infrastructure Type | C23: Unit | D23: Min Unit Cost | E23: Max Unit Cost | F23: Mid Unit Cost | G23: Qty | H23: Total Cost Estimate (Mid) | I23: Total Cost Estimate Range
B24: ORDER 3 TERTIARY LINKS
A25: 1 | B25: Low-Volume Rural Road (basic earth road) | C25: km | D25: =IF('Source Data - In Progress'!C15="","",'Source Data - In Progress'!C15) -> 16213 | E25: =IF('Source Data - In Progress'!D15="","",'Source Data - In Progress'!D15) -> 25099 | F25: =IF('Source Data - In Progress'!E15="","",'Source Data - In Progress'!E15) -> 20656 | G25: 0 | H25: =IFERROR(F25*G25,"") -> 0 | I25: =IFERROR(IF(G25=0,"-",TEXT(D25*G25,"$#,##0")&" - "&TEXT(E25*G25,"$#,##0")),"") -> -
A26: 2 | B26: Low-Volume Rural Road (improved surface) | C26: km | D26: =IF('Source Data - In Progress'!C27="","",'Source Data - In Progress'!C27) -> 88073 | E26: =IF('Source Data - In Progress'!D27="","",'Source Data - In Progress'!D27) -> 156410 | F26: =IF('Source Data - In Progress'!E27="","",'Source Data - In Progress'!E27) -> 122241 | G26: 0 | H26: =IFERROR(F26*G26,"") -> 0 | I26: =IFERROR(IF(G26=0,"-",TEXT(D26*G26,"$#,##0")&" - "&TEXT(E26*G26,"$#,##0")),"") -> -
A27: 3 | B27: Rural Road Bridge (vehicular, simple) | C27: linear foot | D27: =IF('Source Data - In Progress'!C34="","",'Source Data - In Progress'!C34) -> 3048 | E27: =IF('Source Data - In Progress'!D34="","",'Source Data - In Progress'!D34) -> 3981 | F27: =IF('Source Data - In Progress'!E34="","",'Source Data - In Progress'!E34) -> 3515 | G27: 0 | H27: =IFERROR(F27*G27,"") -> 0 | I27: =IFERROR(IF(G27=0,"-",TEXT(D27*G27,"$#,##0")&" - "&TEXT(E27*G27,"$#,##0")),"") -> -
A28: 4 | B28: Fixed Culvert Crossing | C28: linear foot | D28: =IF('Source Data - In Progress'!C43="","",'Source Data - In Progress'!C43) -> 368 | E28: =IF('Source Data - In Progress'!D43="","",'Source Data - In Progress'!D43) -> 545 | F28: =IF('Source Data - In Progress'!E43="","",'Source Data - In Progress'!E43) -> 457 | G28: 0 | H28: =IFERROR(F28*G28,"") -> 0 | I28: =IFERROR(IF(G28=0,"-",TEXT(D28*G28,"$#,##0")&" - "&TEXT(E28*G28,"$#,##0")),"") -> -
A29: 5 | B29: Seasonal Causeway / Low-Water Crossing | C29: crossings | D29: =IF('Source Data - In Progress'!C49="","",'Source Data - In Progress'!C49) -> 20250 | E29: =IF('Source Data - In Progress'!D49="","",'Source Data - In Progress'!D49) -> 26250 | F29: =IF('Source Data - In Progress'!E49="","",'Source Data - In Progress'!E49) -> 23250 | G29: 0 | H29: =IFERROR(F29*G29,"") -> 0 | I29: =IFERROR(IF(G29=0,"-",TEXT(D29*G29,"$#,##0")&" - "&TEXT(E29*G29,"$#,##0")),"") -> -
A30: 6 | B30: Temporary / Emergency Bridge | C30: bridges | D30: =IF('Source Data - In Progress'!C55="","",'Source Data - In Progress'!C55) -> 70000 | E30: =IF('Source Data - In Progress'!D55="","",'Source Data - In Progress'!D55) -> 225000 | F30: =IF('Source Data - In Progress'!E55="","",'Source Data - In Progress'!E55) -> 147500 | G30: 0 | H30: =IFERROR(F30*G30,"") -> 0 | I30: =IFERROR(IF(G30=0,"-",TEXT(D30*G30,"$#,##0")&" - "&TEXT(E30*G30,"$#,##0")),"") -> -
A31: 7 | B31: Stone Arch Bridge | C31: bridges | D31: ='Source Data - In Progress'!C64 -> 46573 | E31: ='Source Data - In Progress'!D64 -> 46573 | F31: ='Source Data - In Progress'!E64 -> 46573 | G31: 0 | H31: =IFERROR(F31*G31,"") -> 0 | I31: =IFERROR(IF(G31=0,"-",TEXT(D31*G31,"$#,##0")&" - "&TEXT(E31*G31,"$#,##0")),"") -> -
B32: SUB-TERTIARY LINKS
A33: 8 | B33: Footpath Construction | C33: km | D33: =IF('Source Data - In Progress'!C75="","",'Source Data - In Progress'!C75) -> 89181 | E33: =IF('Source Data - In Progress'!D75="","",'Source Data - In Progress'!D75) -> 89631 | F33: =IF('Source Data - In Progress'!E75="","",'Source Data - In Progress'!E75) -> 89406 | G33: 0 | H33: =IFERROR(F33*G33,"") -> 0 | I33: =IFERROR(IF(G33=0,"-",TEXT(D33*G33,"$#,##0")&" - "&TEXT(E33*G33,"$#,##0")),"") -> -
A34: 9 | B34: Trail / Track Improvement (IMT-suitable) | C34: km | D34: =IF('Source Data - In Progress'!C82="","",'Source Data - In Progress'!C82) -> 6376 | E34: =IF('Source Data - In Progress'!D82="","",'Source Data - In Progress'!D82) -> 7709 | F34: =IF('Source Data - In Progress'!E82="","",'Source Data - In Progress'!E82) -> 7042 | G34: 0 | H34: =IFERROR(F34*G34,"") -> 0 | I34: =IFERROR(IF(G34=0,"-",TEXT(D34*G34,"$#,##0")&" - "&TEXT(E34*G34,"$#,##0")),"") -> -
A35: 10 | B35: Pedestrian Trail Bridge | C35: linear foot | D35: =IF('Source Data - In Progress'!C89="","",'Source Data - In Progress'!C89) -> 1113 | E35: =IF('Source Data - In Progress'!D89="","",'Source Data - In Progress'!D89) -> 2219 | F35: =IF('Source Data - In Progress'!E89="","",'Source Data - In Progress'!E89) -> 1666 | G35: 0 | H35: =IFERROR(F35*G35,"") -> 0 | I35: =IFERROR(IF(G35=0,"-",TEXT(D35*G35,"$#,##0")&" - "&TEXT(E35*G35,"$#,##0")),"") -> -
A36: 11 | B36: Improvised / Community Bridge (log/plank/bamboo) | C36: linear foot | D36: =IF('Source Data - In Progress'!C94="","",'Source Data - In Progress'!C94) -> 300 | E36: =IF('Source Data - In Progress'!D94="","",'Source Data - In Progress'!D94) -> 600 | F36: =IF('Source Data - In Progress'!E94="","",'Source Data - In Progress'!E94) -> 450 | G36: 0 | H36: =IFERROR(F36*G36,"") -> 0 | I36: =IFERROR(IF(G36=0,"-",TEXT(D36*G36,"$#,##0")&" - "&TEXT(E36*G36,"$#,##0")),"") -> -
A37: 12 | B37: Steel I-Beam Span Bridge | C37: linear foot | D37: =IF('Source Data - In Progress'!C100="","",'Source Data - In Progress'!C100) -> 450 | E37: =IF('Source Data - In Progress'!D100="","",'Source Data - In Progress'!D100) -> 1800 | F37: =IF('Source Data - In Progress'!E100="","",'Source Data - In Progress'!E100) -> 1125 | G37: 0 | H37: =IFERROR(F37*G37,"") -> 0 | I37: =IFERROR(IF(G37=0,"-",TEXT(D37*G37,"$#,##0")&" - "&TEXT(E37*G37,"$#,##0")),"") -> -
A38: 13 | B38: Ferry / Non-Fixed Water Crossing (setup) | C38: crossings | D38: =IF('Source Data - In Progress'!C109="","",'Source Data - In Progress'!C109) -> 6600 | E38: =IF('Source Data - In Progress'!D109="","",'Source Data - In Progress'!D109) -> 28900 | F38: =IF('Source Data - In Progress'!E109="","",'Source Data - In Progress'!E109) -> 21050 | G38: 0 | H38: =IFERROR(F38*G38,"") -> 0 | I38: =IFERROR(IF(G38=0,"-",TEXT(D38*G38,"$#,##0")&" - "&TEXT(E38*G38,"$#,##0")),"") -> -
A39: 14 | B39: Hillside Ladder / Stairway | C39: per meter | D39: =IF('Source Data - In Progress'!C115="","",'Source Data - In Progress'!C115) -> 138 | E39: =IF('Source Data - In Progress'!D115="","",'Source Data - In Progress'!D115) -> 138 | F39: =IF('Source Data - In Progress'!E115="","",'Source Data - In Progress'!E115) -> 138 | G39: 0 | H39: =IFERROR(F39*G39,"") -> 0 | I39: =IFERROR(IF(G39=0,"-",TEXT(D39*G39,"$#,##0")&" - "&TEXT(E39*G39,"$#,##0")),"") -> -
A40: 15 | B40: Ropeway / Cableway | C40: installations | D40: =IF('Source Data - In Progress'!C121="","",'Source Data - In Progress'!C121) -> 8431 | E40: =IF('Source Data - In Progress'!D121="","",'Source Data - In Progress'!D121) -> 11000 | F40: =IF('Source Data - In Progress'!E121="","",'Source Data - In Progress'!E121) -> 9716 | G40: 0 | H40: =IFERROR(F40*G40,"") -> 0 | I40: =IFERROR(IF(G40=0,"-",TEXT(D40*G40,"$#,##0")&" - "&TEXT(E40*G40,"$#,##0")),"") -> -
B41: ANCILLARY & SAFETY INFRASTRUCTURE
A42: 16 | B42: Drainage at Crossings | C42: linear foot | D42: =IF('Source Data - In Progress'!C130="","",'Source Data - In Progress'!C130) -> 20 | E42: =IF('Source Data - In Progress'!D130="","",'Source Data - In Progress'!D130) -> 34 | F42: =IF('Source Data - In Progress'!E130="","",'Source Data - In Progress'!E130) -> 27 | G42: 0 | H42: =IFERROR(F42*G42,"") -> 0 | I42: =IFERROR(IF(G42=0,"-",TEXT(D42*G42,"$#,##0")&" - "&TEXT(E42*G42,"$#,##0")),"") -> -
A43: 17 | B43: Basic Signage / Wayfinding | C43: signs | D43: =IF('Source Data - In Progress'!C137="","",'Source Data - In Progress'!C137) -> 127 | E43: =IF('Source Data - In Progress'!D137="","",'Source Data - In Progress'!D137) -> 365 | F43: =IF('Source Data - In Progress'!E137="","",'Source Data - In Progress'!E137) -> 246 | G43: 0 | H43: =IFERROR(F43*G43,"") -> 0 | I43: =IFERROR(IF(G43=0,"-",TEXT(D43*G43,"$#,##0")&" - "&TEXT(E43*G43,"$#,##0")),"") -> -
A44: 18 | B44: Lighting (solar) | C44: units | D44: =IF('Source Data - In Progress'!C143="","",'Source Data - In Progress'!C143) -> 700 | E44: =IF('Source Data - In Progress'!D143="","",'Source Data - In Progress'!D143) -> 2150 | F44: =IF('Source Data - In Progress'!E143="","",'Source Data - In Progress'!E143) -> 1425 | G44: 0 | H44: =IFERROR(F44*G44,"") -> 0 | I44: =IFERROR(IF(G44=0,"-",TEXT(D44*G44,"$#,##0")&" - "&TEXT(E44*G44,"$#,##0")),"") -> -
A45: 19 | B45: Rest Stop / Waiting Shelter | C45: shelters | D45: =IF('Source Data - In Progress'!C148="","",'Source Data - In Progress'!C148) -> 33681 | E45: =IF('Source Data - In Progress'!D148="","",'Source Data - In Progress'!D148) -> 33681 | F45: =IF('Source Data - In Progress'!E148="","",'Source Data - In Progress'!E148) -> 33681 | G45: 0 | H45: =IFERROR(F45*G45,"") -> 0 | I45: =IFERROR(IF(G45=0,"-",TEXT(D45*G45,"$#,##0")&" - "&TEXT(E45*G45,"$#,##0")),"") -> -
A46: 20 | B46: ICT / Connectivity Point (Wi-Fi/mesh) | C46: installations | D46: ='Source Data - In Progress'!C156 -> 767 | E46: ='Source Data - In Progress'!D156 -> 2900 | F46: ='Source Data - In Progress'!E156 -> 3000 | G46: 0 | H46: =IFERROR(F46*G46,"") -> 0 | I46: =IFERROR(IF(G46=0,"-",TEXT(D46*G46,"$#,##0")&" - "&TEXT(E46*G46,"$#,##0")),"") -> -
A47: 21 | B47: Charging Point (solar) | C47: stations | D47: =IF('Source Data - In Progress'!C162="","",'Source Data - In Progress'!C162) -> 900 | E47: =IF('Source Data - In Progress'!D162="","",'Source Data - In Progress'!D162) -> 3250 | F47: =IF('Source Data - In Progress'!E162="","",'Source Data - In Progress'!E162) -> 2075 | G47: 0 | H47: =IFERROR(F47*G47,"") -> 0 | I47: =IFERROR(IF(G47=0,"-",TEXT(D47*G47,"$#,##0")&" - "&TEXT(E47*G47,"$#,##0")),"") -> -
A48: 22 | B48: Vetiver Grass Slope Stabilization | C48: 100 sq m site | D48: =IF('Source Data - In Progress'!C169="","",'Source Data - In Progress'!C169) -> 1267 | E48: =IF('Source Data - In Progress'!D169="","",'Source Data - In Progress'!D169) -> 3667 | F48: =IF('Source Data - In Progress'!E169="","",'Source Data - In Progress'!E169) -> 2467 | G48: 0 | H48: =IFERROR(F48*G48,"") -> 0 | I48: =IFERROR(IF(G48=0,"-",TEXT(D48*G48,"$#,##0")&" - "&TEXT(E48*G48,"$#,##0")),"") -> -
A49: 23 | B49: Geo Cell / Engineered Slope Stabilization | C49: 100 sq m site | D49: ='Source Data - In Progress'!C181 -> 716 | E49: ='Source Data - In Progress'!D181 -> 5922 | F49: ='Source Data - In Progress'!E181 -> 3319 | G49: 0 | H49: =IFERROR(F49*G49,"") -> 0 | I49: =IFERROR(IF(G49=0,"-",TEXT(D49*G49,"$#,##0")&" - "&TEXT(E49*G49,"$#,##0")),"") -> -
A50: 24 | B50: Jute Netting / Erosion Control | C50: 100 sq m site | D50: =IF('Source Data - In Progress'!C175="","",'Source Data - In Progress'!C175) -> 650 | E50: =IF('Source Data - In Progress'!D175="","",'Source Data - In Progress'!D175) -> 4100 | F50: =IF('Source Data - In Progress'!E175="","",'Source Data - In Progress'!E175) -> 2375 | G50: 0 | H50: =IFERROR(F50*G50,"") -> 0 | I50: =IFERROR(IF(G50=0,"-",TEXT(D50*G50,"$#,##0")&" - "&TEXT(E50*G50,"$#,##0")),"") -> -
B53: SECTION 3: BUDGET SUMMARY
B54: [Info for Cameron/Youdahe Only -- Ideally, this section would be side by side with Section 1 above when its constructed]
B55: Total Infrastructure Cost (Mid-Point Estimate) | C55: =IFERROR(SUM(H24:H50),0) -> 0
B56: Capital Budget Available | C56: =C18 -> 0
B57: Remaining Capital Budget | C57: =C56-C55 -> 0
B58: % of Capital Budget Used | C58: =IF(C18=0,0,C55/C18) -> 0
B59: Maintenance Reserve | C59: =C17 -> 0
B60: Total Estimated RNTI Investment | C60: =C55+C17 -> 0
B61: % of Total Corridor Project | C61: =IF(C12=0,0,C60/C12) -> 0
B64: QUICK REFERENCE: Example Allocation Scenarios
B65: [Info for Cameron/Youdahe Only -- anywhere we could nestle this on the side to be a helpful reference
B66: % Allocation | C66: Budget = $100M | D66: Budget = $200M | E66: Budget = $400M | F66: Budget = $1B
B67: 1% | C67: 1000000 | D67: 2000000 | E67: 4000000 | F67: 10000000
B68: 2% | C68: 2000000 | D68: 4000000 | E68: 8000000 | F68: 20000000
B69: 5% | C69: 5000000 | D69: 10000000 | E69: 20000000 | F69: 50000000
B70: 10% | C70: 10000000 | D70: 20000000 | E70: 40000000 | F70: 100000000

Sheet Source Data - In Progress
A1: RNTI COST SOURCE DATA — Verifiable Sources with Integrated Blended Averages
A2: Each item section lists individual source data points and ends with a BLENDED AVERAGE row (Min / Max / Mid) computed from those points. Items with no verifiable source are intentionally blank for further research. Click source citations to open the original document.
A4: ORDER 3 TERTIARY LINKS
A5: Low-Volume Rural Road (earth) (per km)
A6: # | B6: Geography / Context | C6: Low Est. (USD) | D6: High Est. (USD) | E6: Source Mid | F6: Source Name | G6: Full Citation | H6: Year
A7: 1 | B7: Africa (AfDB 2014 — regraveling of unpaved roads, small projects <100 lane km, Q1-Q3) | C7: 8100 | D7: 10500 | E7: =IFERROR(ROUND((C7+D7)/2,0),"") -> 9300 | F7: AfDB Study on Road Infrastructure Costs 2014 | G7: Source: African Development Bank, Study on Road Infrastructure Costs — Analysis of Unit Costs and Cost Overruns of Road Infrastructure Projects in Africa, May 2014, Table 4-8 (regraveling projects <100 lane km, quartile range) | H7: 2014
A8: 2 | B8: Africa (AfDB 2014 — regraveling of unpaved roads, large projects >=100 lane km, Q1-Q3) | C8: 9600 | D8: 12800 | E8: =IFERROR(ROUND((C8+D8)/2,0),"") -> 11200 | F8: AfDB Study on Road Infrastructure Costs 2014 | G8: Source: AfDB 2014 Study, Table 4-8, regraveling projects >=100 lane km quartile range | H8: 2014
A9: 3 | B9: Global rural (WB Technical Paper 496 — typical basic access road, 2001 USD) | C9: 5000 | D9: 5000 | E9: =IFERROR(ROUND((C9+D9)/2,0),"") -> 5000 | F9: World Bank Technical Paper 496 (2001) | G9: Source: World Bank, Technical Paper No. 496, Design and Appraisal of Rural Transport Infrastructure — Ensuring Basic Access for Rural Communities, 2001, p.20 (typical $5,000/km basic access road) | H9: 2001
A10: 4 | B10: India (WB TP 496 — formation & gravel single-lane rural road, financial cost, 2001 USD) | C10: 5000 | D10: 5000 | E10: =IFERROR(ROUND((C10+D10)/2,0),"") -> 5000 | F10: World Bank Technical Paper 496 (2001) | G10: Source: World Bank TP 496, Table E.1.3, Warangal district rural road paving project, formation + gravel financial capital cost | H10: 2001
A11: 5 | B11: Earth-road construction in mountainous areas: $10,000 to 50,000/km | C11: 10000 | D11: 50000 | E11: =IFERROR(ROUND((C11+D11)/2,0),"") -> 30000 | F11: https://www.ilo.org/sites/default/files/wcmsp5/groups/public/@ed_emp/@emp_policy/@invest/documents/instructionalmaterial/wcms_asist_8494.pdf
A12: 6 | B12: Uganda (unsurfaced roads) | C12: 15000 | D12: 15000 | E12: 15000 | F12: https://assets.publishing.service.gov.uk/media/57a08bd7e5274a27b2000dc3/TI_UP_HD_Feb2007_Cost_of_Roads_in_Africa.pdf
A13: 7 | B13: General global estimate from research | C13: 8000 | D13: 10000 | E13: =IFERROR(ROUND((C13+D13)/2,0),"") -> 9000 | F13: https://assets.publishing.service.gov.uk/media/57a08bd7e5274a27b2000dc3/TI_UP_HD_Feb2007_Cost_of_Roads_in_Africa.pdf
B14: [Rwanda numbers] | C14: 69000 | D14: 92495 | E14: =IFERROR(ROUND((C14+D14)/2,0),"") -> 80748 | F14: https://blogs.worldbank.org/en/nasikiliza/road-to-prosperity-how-feeder-roads-are-creating-jobs-and-transforming-lives-in-rural-rwanda-afe-0425 | H14: 2025
B15: BLENDED AVERAGE (Min / Max / Mid) | C15: =IFERROR(ROUND(AVERAGE(C7:C14),0),"") -> 16213 | D15: =IFERROR(ROUND(AVERAGE(D7:D14),0),"") -> 25099 | E15: =IFERROR(ROUND(AVERAGE(E7:E14),0),"") -> 20656
A17: Low-Volume Rural Road (improved surface) (per km)
A18: # | B18: Geography / Context | C18: Low Est. (USD) | D18: High Est. (USD) | E18: Source Mid | F18: Source Name | G18: Full Citation | H18: Year
A19: 1 | B19: Africa (AfDB 2014 — construction/upgrade of paved roads, small projects <100 lane km, Q1-Q3) | C19: 166300 | D19: 425400 | E19: =IFERROR(ROUND((C19+D19)/2,0),"") -> 295850 | F19: AfDB Study on Road Infrastructure Costs 2014 | G19: Source: AfDB 2014 Study, Table 4-5, construction/upgrading paved road projects <100 lane km, Q1-Q3 range | H19: 2014
A20: 2 | B20: Africa (AfDB 2014 — rehabilitation of paved roads, small projects <100 lane km, Q1-Q3) | C20: 109800 | D20: 290000 | E20: =IFERROR(ROUND((C20+D20)/2,0),"") -> 199900 | F20: AfDB Study on Road Infrastructure Costs 2014 | G20: Source: AfDB 2014 Study, Table 4-6, rehabilitation paved road projects <100 lane km, Q1-Q3 range | H20: 2014
A21: 3 | B21: Ghana (MCC Compact — Feeder Road Activity, 357 km for $71 M) | C21: 198880 | D21: 198880 | E21: =IFERROR(ROUND((C21+D21)/2,0),"") -> 198880 | F21: MCC Ghana Transportation Final Evaluation Brief 2020 | G21: Source: Millennium Challenge Corporation, Improving Roads to Reduce Transportation Costs in Ghana, Final Evaluation Brief, September 2020 ($71 M / 357 km rehabilitated feeder roads) | H21: 2020
A22: 4 | B22: India (WB TP 496 — surface treatment 6.5m wide, 2001 USD) | C22: 125000 | D22: 125000 | E22: =IFERROR(ROUND((C22+D22)/2,0),"") -> 125000 | F22: World Bank Technical Paper 496 (2001) | G22: Source: World Bank TP 496, Appendix F, Example 1 (surface treatment paving option, 6.5 m wide) | H22: 2001
A23: 5 | B23: India (WB TP 496 — concrete block 4.0 m / 6.5 m wide, 2001 USD) | C23: 48000 | D23: 78000 | E23: =IFERROR(ROUND((C23+D23)/2,0),"") -> 63000 | F23: World Bank Technical Paper 496 (2001) | G23: Source: World Bank TP 496, Appendix F, Example 1 (concrete block paving, 4.0 m and 6.5 m widths) | H23: 2001
A24: 6 | B24: India (WB TP 496 — India standard full rural road, 2001 USD) | C24: 40000 | D24: 40000 | E24: =IFERROR(ROUND((C24+D24)/2,0),"") -> 40000 | F24: World Bank Technical Paper 496 (2001) | G24: Source: World Bank TP 496, p.85 footnote (India standard single-lane rural road with 2cm bituminous + triple WBM + gravel layer) | H24: 2001
A25: 7 | B25: Rural Roads (China) | C25: 6600 | D25: 79000 | E25: =IFERROR(ROUND((C25+D25)/2,0),"") -> 42800 | F25: https://fsi-live.s3.us-west-1.amazonaws.com/s3fs-public/wong-et-al-2013-providing_quality_infrastructure.pdf | H25: 2007
A26: 8 | B26: General global estimate from research | C26: 10000 | D26: 15000 | E26: =IFERROR(ROUND((C26+D26)/2,0),"") -> 12500 | F26: https://assets.publishing.service.gov.uk/media/57a08bd7e5274a27b2000dc3/TI_UP_HD_Feb2007_Cost_of_Roads_in_Africa.pdf
B27: BLENDED AVERAGE (Min / Max / Mid) | C27: =IFERROR(ROUND(AVERAGE(C19:C26),0),"") -> 88073 | D27: =IFERROR(ROUND(AVERAGE(D19:D26),0),"") -> 156410 | E27: =IFERROR(ROUND(AVERAGE(E19:E26),0),"") -> 122241
A29: Rural Road Bridge (vehicular, simple) (per LF of deck)
A30: # | B30: Geography / Context | C30: Low Est. (USD) | D30: High Est. (USD) | E30: Source Mid | F30: Source Name | G30: Full Citation | H30: Year
A31: 1 | B31: Global (Evercross 2024 — beam bridges, material + construction) | C31: 400 | D31: 1600 | E31: =IFERROR(ROUND((C31+D31)/2,0),"") -> 1000 | F31: Evercross Bridge, How Much Does It Cost To Build A Pedestrian Bridge? (2024) | G31: Source: Evercross Bridge / Bailey Bridge Solution, How Much Does It Cost To Build A Pedestrian Bridge?, 2024-12-16 (beam bridges $400-$1,600/LF; applied here as simple vehicular beam bridge analogue) | H31: 2024
A32: 2 | B32: India (WB TP 496 — major cross-drainage structure, per m of span, 2001 USD) | C32: 1143 | D32: 1143 | E32: =IFERROR(ROUND((C32+D32)/2,0),"") -> 1143 | F32: World Bank Technical Paper 496 (2001) | G32: Source: World Bank TP 496, Table E.1.3, Major CD $3,750/m financial capital cost converted to $/LF ($3,750 / 3.28 ft/m) | H32: 2001
A33: 3 | B33: US: single-lane rural bridge 20ft -24ft wide x 40 ft span | C33: 7600 | D33: 9200 | E33: =IFERROR(ROUND((C33+D33)/2,0),"") -> 8400 | F33: https://www.fhwa.dot.gov/bridge/nbi/sd2024.cfm | G33: Source: US D.O.T. FHA | H33: 2024 | I33: 20 ft (single lane, standard rural) $383/ft^2 = $7660/LF 24 ft = $9200/LF
B34: BLENDED AVERAGE (Min / Max / Mid) | C34: =IFERROR(ROUND(AVERAGE(C31:C33),0),"") -> 3048 | D34: =IFERROR(ROUND(AVERAGE(D31:D33),0),"") -> 3981 | E34: =IFERROR(ROUND((C34+D34)/2,0),"") -> 3515
A36: Fixed Culvert Crossing (per LF, installed)
A37: # | B37: Geography / Context | C37: Low Est. (USD) | D37: High Est. (USD) | E37: Source Mid | F37: Source Name | G37: Full Citation | H37: Year
A38: 1 | B38: USA (Fairfax County VA — 4'x4' single box culvert) | C38: 533 | D38: 533 | E38: =IFERROR(ROUND((C38+D38)/2,0),"") -> 533 | F38: Fairfax County FY2026 Unit Price Schedule | G38: Source: Fairfax County Public Works, Unit Price Schedule, FY2026 (Feb 2026), Storm Sewer — Culverts, Single Box Culvert 4'x4' | H38: 2026
A39: 2 | B39: USA (Fairfax County VA — 8'x8' to 12'x8' box culvert) | C39: 1092 | D39: 1703 | E39: =IFERROR(ROUND((C39+D39)/2,0),"") -> 1398 | F39: Fairfax County FY2026 Unit Price Schedule | G39: Source: Fairfax County Public Works, Unit Price Schedule, FY2026 (Feb 2026), Single/Oversized Box Culvert 8'x8' to 12'x8' | H39: 2026
A40: 3 | B40: Kenya (Lower Eastern — 900mm pipe culvert, with/without surround, installed) | C40: 58 | D40: 151 | E40: =IFERROR(ROUND((C40+D40)/2,0),"") -> 105 | F40: Kenya Cost Estimation Manual 2025 (Lower Eastern) | G40: Source: Republic of Kenya, Cost Estimation Manual for Road Construction and Maintenance Works 2025 — Lower Eastern Region, Items 08.60.026/027 (900mm pipe culvert), KES 5,719-19,673/m converted at 130 KES/USD and 3.28 ft/m | H40: 2025
A41: 4 | B41: Kenya (Lower Eastern — 1200mm pipe culvert, with/without surround, installed) | C41: 105 | D41: 256 | E41: =IFERROR(ROUND((C41+D41)/2,0),"") -> 181 | F41: Kenya Cost Estimation Manual 2025 (Lower Eastern) | G41: Source: Republic of Kenya, Cost Estimation Manual 2025 — Lower Eastern Region, Items 08.60.028/029 (1200mm pipe culvert), KES 10,356-33,284/m converted | H41: 2025
A42: 5 | B42: USA (Pennsylvania DGLVR — 24"-36" HDPE pipe culvert, installed) | C42: 50 | D42: 80 | E42: =IFERROR(ROUND((C42+D42)/2,0),"") -> 65 | F42: Pennsylvania DGLVR Program Typical Costs 2015 | G42: Source: Penn State Center for Dirt and Gravel Road Studies, DGLVR Program Summary of Typical Costs, April 2015, Drainage section — 24"-36" HDPE dual-wall smooth bore | H42: 2015
B43: BLENDED AVERAGE (Min / Max / Mid) | C43: =IFERROR(ROUND(AVERAGE(C38:C42),0),"") -> 368 | D43: =IFERROR(ROUND(AVERAGE(D38:D42),0),"") -> 545 | E43: =IFERROR(ROUND((C43+D43)/2,0),"") -> 457
A45: Seasonal Causeway / Low-Water Crossing (per crossing)
A46: # | B46: Geography / Context | C46: Low Est. (USD) | D46: High Est. (USD) | E46: Source Mid | F46: Source Name | G46: Full Citation | H46: Year
A47: 1 | B47: USA (Forest Service — unvented ford) | C47: 500 | D47: 2500 | E47: =IFERROR(ROUND((C47+D47)/2,0),"") -> 1500 | F47: USDA Forest Service | G47: Low-Water Crossings: Geomorphic, Biological, and Engineering Design Considerations — Table 2.1 reports unvented ford construction costs of roughly $500–$2,500 per site. | H47: 2006
A48: 2 | B48: USA (Illinois — concrete low-water bridge) | C48: 40000 | D48: 50000 | E48: =IFERROR(ROUND((C48+D48)/2,0),"") -> 45000 | F48: Illinois DNR / USFS case study | G48: Illinois case reported in USFS low-water crossings manual: concrete low-water bridge crossings constructed for approximately $40,000–$50,000 per site. | H48: 2006
B49: BLENDED AVERAGE (Min / Max / Mid) | C49: =IFERROR(ROUND(AVERAGE(C47:C48),0),"") -> 20250 | D49: =IFERROR(ROUND(AVERAGE(D47:D48),0),"") -> 26250 | E49: =IFERROR(ROUND((C49+D49)/2,0),"") -> 23250
A51: Temporary / Emergency Bridge (per bridge)
A52: # | B52: Geography / Context | C52: Low Est. (USD) | D52: High Est. (USD) | E52: Source Mid | F52: Source Name | G52: Full Citation | H52: Year
A53: 1 | B53: Global (Bailey / modular panel bridge) | C53: 90000 | D53: 200000 | E53: =IFERROR(ROUND((C53+D53)/2,0),"") -> 145000 | F53: EverCross / Bailey Bridge industry data | G53: Bailey/modular panel bridge supply and erection commonly quoted at roughly $30–$50 per linear foot of deck area; a 60–80 ft single-lane span therefore falls in the ~$90k–$200k range for components plus local erection. | H53: 2023
A54: 2 | B54: Global (portable modular emergency bridge) | C54: 50000 | D54: 250000 | E54: =IFERROR(ROUND((C54+D54)/2,0),"") -> 150000 | F54: Acrow / Mabey Bridge product literature | G54: Acrow and Mabey portable modular emergency bridges: short single-lane spans typically $50k–$250k depending on span length, deck width and delivery distance. | H54: 2022
B55: BLENDED AVERAGE (Min / Max / Mid) | C55: =IFERROR(ROUND(AVERAGE(C53:C54),0),"") -> 70000 | D55: =IFERROR(ROUND(AVERAGE(D53:D54),0),"") -> 225000 | E55: =IFERROR(ROUND((C55+D55)/2,0),"") -> 147500
A57: Stonearch Bridge
A58: # | B58: Geography / Context | C58: Low Est. (USD) | D58: High Est. (USD) | E58: Source Mid | F58: Source Name | G58: Full Citation | H58: Year
A59: 1 | B59: Kachingwe BOQ (Zambia) | C59: 74254 | D59: 74254 | E59: 74254 | F59: Fika | H59: 2023
A60: 2 | B60: Rwebeya BOQ (Rwanda) | C60: 31135 | D60: 31135 | E60: 31135 | F60: Fika
A61: 3 | B61: Nyakaruru BOQ (Rwanda) | C61: 41579 | D61: 41579 | E61: 41579 | F61: Fika
A62: 4 | B62: Buhoro BOQ (Rwanda) | C62: 38997 | D62: 38997 | E62: 38997 | F62: Fika
A63: 5 | B63: Enabel Stone Arch Average (Tanzania) | C63: 46900 | D63: 46900 | E63: 46900 | F63: https://www.globalconstructionreview.com/stone-age-bridge-revolution-gets-tanzania-moving/
B64: BLENDED AVERAGE (Min / Max / Mid) | C64: =IFERROR(ROUND(AVERAGE(C59:C63),0),"") -> 46573 | D64: =IFERROR(ROUND(AVERAGE(D59:D63),0),"") -> 46573 | E64: =IFERROR(ROUND(AVERAGE(E59:E63),0),"") -> 46573
A66: SUB-TERTIARY LINKS
A67: Footpath Construction (per km)
A68: # | B68: Geography / Context | C68: Low Est. (USD) | D68: High Est. (USD) | E68: Source Mid | F68: Source Name | G68: Full Citation | H68: Year
A69: 1 | B69: Honey Creek Parkway Construction of bike trail from Portland Ave to 70th St, not including bridge construction, is $149,206 per mile for 10 foot wide asphalt trail (USA) | C69: 92712 | D69: 92712 | E69: 92712 | F69: Link
A70: 2 | B70: South Side Trail (a.k.a. Kinnickinnic River Bicycle Trail) for base construction including trail amenities, signage, and drainage issues is $176,470 per mile for a 10 foot wide asphalt trail (USA) | C70: 109653 | D70: 109653 | E70: 109653 | F70: Link
A71: 3 | B71: Root River, from 60th St. under Hwy 100 to Rainbow Airport, not including boardwalk is $301,014 per mile for 10 foot wide asphalt trail* (USA) | C71: 187041 | D71: 187041 | E71: 187041 | F71: Link
A72: 4 | B72: Milwaukee County's estimate for construction of the 6.5 mile Hank Aaron State Trail (West Allis Line) is $224,307 per mile for a 10 foot wide asphalt trail (including retrofit of bridges) (USA) | C72: 139378 | D72: 139378 | E72: 139378 | F72: Link
A73: 5 | B73: Footpath-to-motorcycle track (Liberia) | C73: 3300 | D73: 5000 | E73: =(C73+D73)/2 -> 4150 | F73: https://fika-org.box.com/s/upnsgk1tfkw27y4u5hlg6jui9ds63gse
A74: 6 | B74: 2m wide track (Liberia) | C74: 3000 | D74: 4000 | E74: =(C74+D74)/2 -> 3500 | F74: https://www.emerald.com/jtran/article/169/6/378/407154/Rural-connectivity-in-Africa-motorcycle-track
B75: BLENDED AVERAGE (Min / Max / Mid) | C75: =IFERROR(ROUND(AVERAGE(C69:C74),0),"") -> 89181 | D75: =IFERROR(ROUND(AVERAGE(D69:D74),0),"") -> 89631 | E75: =IFERROR(ROUND(AVERAGE(E69:E74),0),"") -> 89406
A77: Trail / Track Improvement (IMT-suitable) (per km)
A78: # | B78: Geography / Context | C78: Low Est. (USD) | D78: High Est. (USD) | E78: Source Mid | F78: Source Name | G78: Full Citation | H78: Year
A79: 1 | B79: Zimbabwe (labor-based rural track rehab) | C79: 13000 | D79: 14000 | E79: =IFERROR(ROUND((C79+D79)/2,0),"") -> 13500 | F79: ILO ASIST / World Bank SSATP | G79: Zimbabwe labor-based rural track rehabilitation reported at approximately $13,000–$14,000 per kilometer under the ASIST programme. | H79: 2005
A80: 2 | B80: Uganda (labor-based periodic maintenance) | C80: 6000 | D80: 9000 | E80: =IFERROR(ROUND((C80+D80)/2,0),"") -> 7500 | F80: World Bank SSATP Working Paper | G80: Uganda labor-based periodic maintenance of rural tracks averaged roughly $6,000–$9,000 per km, with reported averages near $7,800/km. | H80: 2005
B81: Lesotho (labor-based annual) | C81: 127 | D81: 127 | E81: =IFERROR(ROUND((C81+D81)/2,0),"") -> 127 | F81: https://assets.publishing.service.gov.uk/media/57a08bd7e5274a27b2000dc3/TI_UP_HD_Feb2007_Cost_of_Roads_in_Africa.pdf
B82: BLENDED AVERAGE (Min / Max / Mid) | C82: =IFERROR(ROUND(AVERAGE(C79:C81),0),"") -> 6376 | D82: =IFERROR(ROUND(AVERAGE(D79:D81),0),"") -> 7709 | E82: =IFERROR(ROUND(AVERAGE(E79:E81),0),"") -> 7042
A84: Pedestrian Trail Bridge (cable suspension / cable-stayed) (per LF of deck)
A85: # | B85: Geography / Context | C85: Low Est. (USD) | D85: High Est. (USD) | E85: Source Mid | F85: Source Name | G85: Full Citation | H85: Year
A86: 1 | B86: Global (Evercross 2024 — cable-stayed pedestrian bridges) | C86: 1000 | D86: 3000 | E86: =IFERROR(ROUND((C86+D86)/2,0),"") -> 2000 | F86: Evercross Bridge, How Much Does It Cost To Build A Pedestrian Bridge? (2024) | G86: Source: Evercross Bridge / Bailey Bridge Solution, 2024-12-16, cable-stayed pedestrian bridges $1,000-$3,000/LF | H86: 2024
A87: 2 | B87: Global (Evercross 2024 — suspension pedestrian bridges) | C87: 2000 | D87: 3000 | E87: =IFERROR(ROUND((C87+D87)/2,0),"") -> 2500 | F87: Evercross Bridge, How Much Does It Cost To Build A Pedestrian Bridge? (2024) | G87: Source: Evercross Bridge, 2024-12-16, suspension bridges 'upwards of $2,000/LF' (range $2,000-$3,000 estimated for fully suspended structures) | H87: 2024
A88: 3 | B88: Fika General Average (67.217198 meters across our 800 bridges) | C88: 340.09 | D88: 657.51 | E88: =IFERROR(ROUND((C88+D88)/2,0),"") -> 499 | F88: Fika estimates (75k-145k per bridge)
B89: BLENDED AVERAGE (Min / Max / Mid) | C89: =IFERROR(ROUND(AVERAGE(C86:C88),0),"") -> 1113 | D89: =IFERROR(ROUND(AVERAGE(D86:D88),0),"") -> 2219 | E89: =IFERROR(ROUND(AVERAGE(E86:E88),0),"") -> 1666
A91: Improvised / Community Bridge (log, plank, bamboo) (per LF of deck)
A92: # | B92: Geography / Context | C92: Low Est. (USD) | D92: High Est. (USD) | E92: Source Mid | F92: Source Name | G92: Full Citation | H92: Year
A93: 1 | B93: Global (Evercross 2024 — wooden pedestrian bridges, simple timber) | C93: 300 | D93: 600 | E93: =IFERROR(ROUND((C93+D93)/2,0),"") -> 450 | F93: Evercross Bridge, How Much Does It Cost To Build A Pedestrian Bridge? (2024) | G93: Source: Evercross Bridge, 2024-12-16, wooden pedestrian bridges $300-$600/LF | H93: 2024
B94: BLENDED AVERAGE (Min / Max / Mid) | C94: =IFERROR(ROUND(AVERAGE(C93),0),"") -> 300 | D94: =IFERROR(ROUND(AVERAGE(D93),0),"") -> 600 | E94: =IFERROR(ROUND((C94+D94)/2,0),"") -> 450
A96: Steel I-Beam Span Bridge (per LF of deck)
A97: # | B97: Geography / Context | C97: Low Est. (USD) | D97: High Est. (USD) | E97: Source Mid | F97: Source Name | G97: Full Citation | H97: Year
A98: 1 | B98: Global (Evercross 2024 — steel beam bridges) | C98: 400 | D98: 1600 | E98: =IFERROR(ROUND((C98+D98)/2,0),"") -> 1000 | F98: Evercross Bridge, How Much Does It Cost To Build A Pedestrian Bridge? (2024) | G98: Source: Evercross Bridge, 2024-12-16, steel beam bridges $400-$1,600/LF | H98: 2024
A99: 2 | B99: Global (Evercross 2024 — steel truss pedestrian bridges) | C99: 500 | D99: 2000 | E99: =IFERROR(ROUND((C99+D99)/2,0),"") -> 1250 | F99: Evercross Bridge, How Much Does It Cost To Build A Pedestrian Bridge? (2024) | G99: Source: Evercross Bridge, 2024-12-16, steel truss bridges $500-$2,000/LF | H99: 2024
B100: BLENDED AVERAGE (Min / Max / Mid) | C100: =IFERROR(ROUND(AVERAGE(C98:C99),0),"") -> 450 | D100: =IFERROR(ROUND(AVERAGE(D98:D99),0),"") -> 1800 | E100: =IFERROR(ROUND((C100+D100)/2,0),"") -> 1125
A102: Ferry / Non-Fixed Water Crossing (setup) (per crossing)
A103: # | B103: Geography / Context | C103: Low Est. (USD) | D103: High Est. (USD) | E103: Source Mid | F103: Source Name | G103: Full Citation | H103: Year
A104: 1 | B104: Floating Dock (USA) | C104: 3000 | D104: 17500 | E104: =C104+D104/2 -> 11750 | F104: https://www.dockgearsupply.com/blogs/blog/dock-building-costs-in-2025-full-price-breakdown-guide
A105: 2 | B105: Piling Dock (USA) | C105: 4000 | D105: 20000 | E105: =C105+D105/2 -> 14000 | F105: https://www.dockgearsupply.com/blogs/blog/dock-building-costs-in-2025-full-price-breakdown-guide
A106: 3 | B106: Crib Dock (USA) | C106: 10000 | D106: 50000 | E106: =C106+D106/2 -> 35000 | F106: https://www.dockgearsupply.com/blogs/blog/dock-building-costs-in-2025-full-price-breakdown-guide
A107: 4 | B107: Aluminum Pipe (USA) | C107: 1000 | D107: 7000 | E107: =C107+D107/2 -> 4500 | F107: https://www.dockgearsupply.com/blogs/blog/dock-building-costs-in-2025-full-price-breakdown-guide
A108: 5 | B108: Double-Decker (USA) | C108: 15000 | D108: 50000 | E108: =C108+D108/2 -> 40000 | F108: https://www.dockgearsupply.com/blogs/blog/dock-building-costs-in-2025-full-price-breakdown-guide
B109: BLENDED AVERAGE (Min / Max / Mid) | C109: =IFERROR(ROUND(AVERAGE(C104:C108),0),"") -> 6600 | D109: =IFERROR(ROUND(AVERAGE(D104:D108),0),"") -> 28900 | E109: =IFERROR(ROUND(AVERAGE(E104:E108),0),"") -> 21050
A111: Hillside Ladder / Stairway (per installation)
A112: # | B112: Geography / Context | C112: Low Est. (USD) | D112: High Est. (USD) | E112: Source Mid | F112: Source Name | G112: Full Citation | H112: Year
A113: 1 | B113: Steel Ladder Steps/meter | C113: 175 | D113: 175 | E113: 175 | F113: Uganda MELTC Engineer | H113: 2026
A114: 2 | B114: Stone Masonry steps/cubic meter | C114: 100 | D114: 100 | E114: 100 | F114: Uganda MELTC Engineer | H114: 2026
...

Sheet Info for CamYoudahe
A1: CORRIDOR ADD-ON CALCULATOR — RNTI BUDGET PLANNING TOOL
B3: PURPOSE
B4: This tool helps rural transport planners estimate what Rural Networked Transport Infrastructure (RNTI)
B5: investments could be funded by allocating a small percentage of a larger corridor-level transport budget.
B6: It is intended as a conversation starter — not a final costing tool.
B8: HOW TO USE
B9: 1. Go to the 'Budget Calculator' sheet.
B10: 2. Enter your total corridor project budget (USD) in the yellow input cell.
B11: 3. Enter the percentage of that budget to allocate to RNTI (e.g., 1%, 5%, 10%).
B12: 4. Optionally adjust the maintenance reserve percentage.
B13: 5. In the Infrastructure Mix table, enter a quantity next to any RNTI type you want to fund.
B14: 6. The tool auto-calculates total costs, remaining budget, and a summary at the bottom.
B16: COLOR CODING
... B53: AfDB (2014). Study on Road Infrastructure Costs: Analysis of Unit Costs and Cost Overruns.

Sheet RNTI Components
A1: TABLE 1: RNTI COMPONENTS (Segerberg & Noriega, 2026)
B2: Source: Sustainability 2026, 18, 2842. https://doi.org/10.3390/su18062842
B4: Link Order | C4: Order 3 Tertiary Links (Road Dominant) | D4: Sub-Tertiary Links (Paths, Trails, Crossings)
B5: Corridor Level | C5: Inter-/intra-district; connects clusters of villages and local centers to all-weather roads and higher-order networks. In riverine contexts, connectivity may also be provided by water-based connectors. | D5: Hyperlocal; connects dispersed households, farms, and hamlets to the nearest tertiary link or community connector.
B6: Primary Function | C6: Facilitates movement of goods and people between villages, agricultural zones, markets, and service hubs. | D6: Provides first-/last-mile access by connecting households and farms to tertiary links and nearby services.
B7: Typical Users | C7: Local residents; smallholder and commercial farmers; informal transport operators. | D7: Rural households; school children; pedestrians; subsistence farmers; informal transporters.
B8: Typical Transport Modes | C8: Mixed traffic, including light motorized vehicles (e.g., small trucks, tricycles, motorcycles), IMTs (e.g., animal-drawn carts, bicycles, rickshaws). | D8: Predominantly NMT (walking, bicycles, livestock, handcarts). In riverine contexts, may include indigenous watercrafts and small motorized modes.
B9: Types of Infrastructure Links | C9: LVRs: unpaved rural roads, tracks suitable for IMT. Informal/ghost roads. Engineered bridges & fixed crossings. Seasonal causeways/low-water crossings. Temporary/emergency links. | D9: Low-capacity paths, trails, tracks. Improvised crossings (log, plank, bamboo bridges). Engineered trail bridges (cable trail bridges). Non-fixed crossings (ferries, canoes). Vertical/non-standard links (ladders, ropeways).
B10: Emerging Access (Non-link) | C10: N/A | D10: Drones and UAVs via aerial routes and associated support infrastructure.
B11: Engineering & Formality | C11: Generally engineered or semi-engineered; formally planned and maintained through district/national agencies. | D11: Predominantly non-engineered and informally developed by communities; some types may be formally built.
B12: Ancillary & Safety Infrastructure | C12: Drainage, signage/reflectors, waiting shelters, embankments, safety features. Context-dependent: lighting, ICT, charging points. | D12: Drainage at crossings, wayfinding/signage, benches/rest points, informal repair services. Emerging: ICT, charging points, rest stops.
B14: IMT = Intermediate Modes of Transport; LVR = Low-Volume Road; ICT = Information & Communication Technology; NMT = Non-Motorized Transport; UAV = Unmanned Aerial Vehicle
